[1,["0bGspnl6BFv5LrEBMnba6v@6c48a"],["_textureSource"],["cc.SpriteFrame"],0,[{"name":"gang_tie_zhan_zhu","rect":{"x":8,"y":8,"width":180,"height":184},"offset":{"x":-2,"y":0},"originalSize":{"width":200,"height":200},"rotated":false,"capInsets":[0,0,0,0],"vertices":{"rawPosition":[-90,-92,0,90,-92,0,-90,92,0,90,92,0],"indexes":[0,1,2,2,1,3],"uv":[8,192,188,192,8,8,188,8],"nuv":[0.04,0.04,0.94,0.04,0.04,0.96,0.94,0.96],"minPos":{"x":-90,"y":-92,"z":0},"maxPos":{"x":90,"y":92,"z":0}},"packable":true,"pixelsToUnit":100,"pivot":{"x":0.5,"y":0.5},"meshType":0}],[0],0,[0],[0],[0]]
